MANIFEST.in
README.rst
setup.py
django_suit_ckeditor.egg-info/PKG-INFO
django_suit_ckeditor.egg-info/SOURCES.txt
django_suit_ckeditor.egg-info/dependency_links.txt
django_suit_ckeditor.egg-info/not-zip-safe
django_suit_ckeditor.egg-info/top_level.txt
suit_ckeditor/__init__.py
suit_ckeditor/models.py
suit_ckeditor/widgets.py
suit_ckeditor/static/suit-ckeditor/ckeditor.css
suit_ckeditor/static/suit-ckeditor/ckeditor/CHANGES.md
suit_ckeditor/static/suit-ckeditor/ckeditor/LICENSE.md
suit_ckeditor/static/suit-ckeditor/ckeditor/README.md
suit_ckeditor/static/suit-ckeditor/ckeditor/build-config.js
suit_ckeditor/static/suit-ckeditor/ckeditor/ckeditor.js
suit_ckeditor/static/suit-ckeditor/ckeditor/config.js
suit_ckeditor/static/suit-ckeditor/ckeditor/contents.css
suit_ckeditor/static/suit-ckeditor/ckeditor/styles.js
suit_ckeditor/static/suit-ckeditor/ckeditor/lang/af.js
suit_ckeditor/static/suit-ckeditor/ckeditor/lang/ar.js
suit_ckeditor/static/suit-ckeditor/ckeditor/lang/bg.js
suit_ckeditor/static/suit-ckeditor/ckeditor/lang/bn.js
suit_ckeditor/static/suit-ckeditor/ckeditor/lang/bs.js
suit_ckeditor/static/suit-ckeditor/ckeditor/lang/ca.js
suit_ckeditor/static/suit-ckeditor/ckeditor/lang/cs.js
suit_ckeditor/static/suit-ckeditor/ckeditor/lang/cy.js
suit_ckeditor/static/suit-ckeditor/ckeditor/lang/da.js
suit_ckeditor/static/suit-ckeditor/ckeditor/lang/de.js
suit_ckeditor/static/suit-ckeditor/ckeditor/lang/el.js
suit_ckeditor/static/suit-ckeditor/ckeditor/lang/en-au.js
suit_ckeditor/static/suit-ckeditor/ckeditor/lang/en-ca.js
suit_ckeditor/static/suit-ckeditor/ckeditor/lang/en-gb.js
suit_ckeditor/static/suit-ckeditor/ckeditor/lang/en.js
suit_ckeditor/static/suit-ckeditor/ckeditor/lang/eo.js
suit_ckeditor/static/suit-ckeditor/ckeditor/lang/es.js
suit_ckeditor/static/suit-ckeditor/ckeditor/lang/et.js
suit_ckeditor/static/suit-ckeditor/ckeditor/lang/eu.js
suit_ckeditor/static/suit-ckeditor/ckeditor/lang/fa.js
suit_ckeditor/static/suit-ckeditor/ckeditor/lang/fi.js
suit_ckeditor/static/suit-ckeditor/ckeditor/lang/fo.js
suit_ckeditor/static/suit-ckeditor/ckeditor/lang/fr-ca.js
suit_ckeditor/static/suit-ckeditor/ckeditor/lang/fr.js
suit_ckeditor/static/suit-ckeditor/ckeditor/lang/gl.js
